tuma_ai/AI.py
tuma_ai/__init__.py
tuma_ai/enums.py
tuma_ai-1.2.2.dist-info/LICENSE
tuma_ai-1.2.2.dist-info/METADATA
tuma_ai-1.2.2.dist-info/WHEEL
tuma_ai-1.2.2.dist-info/top_level.txt
tuma_ai-1.2.2.dist-info/RECORD
