Metadata-Version: 2.1
Name: tuma-ai
Version: 1.2.2
Summary: 适合编程教学学习使用的AI库
Home-page: https://gitee.com/tangyuqi-code/tuma-ai
Author: Tangyuqi
Author-email: 644853320@qq.com
Requires-Python: >=3.6
License-File: LICENSE
